pyZlBus2/__init__.py
pyZlBus2/pyZlBus2.py
pyZlBus2/pyZlBusBleTest.py
pyZlBus2/pyZlBusSerialRfTest.py
pyZlBus2/pyZlBusSerialTest.py
pyZlBus2/pyZlBusTest.py
pyzlbus2-0.1.8.dist-info/LICENSE
pyzlbus2-0.1.8.dist-info/METADATA
pyzlbus2-0.1.8.dist-info/WHEEL
pyzlbus2-0.1.8.dist-info/top_level.txt
pyzlbus2-0.1.8.dist-info/RECORD
