Metadata-Version: 2.1
Name: pyzlbus2
Version: 0.1.8
Summary: ZeroLab Bus API for Python
Author: ZeroLab
Author-email: larry.lv@zero-lab.tech
Classifier: Programming Language :: Python :: 3
Classifier: Programming Language :: Python :: 3.8
Classifier: License :: OSI Approved :: MIT License
Classifier: Operating System :: OS Independent
Requires-Python: >=3.8
License-File: LICENSE
Requires-Dist: bleak >=0.21.0
Requires-Dist: pyserial >=3.4
Requires-Dist: zlbusapi >=0.5.7
